{
    "scan": {
        "scan_id": "ca495e5ef260",
        "evaluation_type": "performance",
        "started": "2020-05-06T18:56:10",
        "ended": "2020-05-06T18:56:10",
        "name": "Baseline evaluation of 3 models",
        "description": "This evaluation compares the robustness, accuracy, fairness and explanations for 3 candidate models."
    },
    "model_use_case": {
        "name": "Insurance: Auto Insurance Claims",
        "model_use_case_id": "c12e/datasciencelab/auto_insurance",
        "performance_metrics": [
            {
                "metric": "R-squared",
                "name": "R-squared"
            }
        ],
        "atx_performance_metric_name": "R-squared",
        "task_type": "regression",
        "description": "In this use case, each entry in the dataset represents an auto insurance claim. The learning task is to predict the final settled claim amount.\n\nThis dataset was originally sourced from Emcien: https://www.sixtusdakurah.com/resources/The_Application_of_Regularization_in_Modelling_Insurance_Claims.pdf\n",
        "author": "info@cognitivescale.com"
    },
    "model": {
        "model_id": "svr",
        "name": "Support Vector Regression",
        "predict_endpoint": "http://127.0.0.1:5111/auto_insurance_svr/predict",
        "description": "Scikit-learn SVR regression"
    },
    "status": "Completed",
    "dataset": {
        "dataset_id": "test",
        "url": "file:../datasets/auto_insurance_test.csv",
        "checksum_type": "md5",
        "checksum": "25c2a0f644f02cbc7858327796e87b35",
        "num_features": 20,
        "rows": 2741,
        "name": "Test dataset",
        "description": "2741 row test dataset"
    },
    "performance_metrics": [
        {
            "name": "R-squared",
            "value": 0.8305159069339683,
            "score": 83.05159069339683
        }
    ]
}